[
  {
    "slug": "rawdat-al-sidr",
    "title_en": "Rawdat Al Sidr",
    "title_ar": "روضة السدر – مشروع سكني تجاري متكامل في موقع استراتيجي",
    "location_en": "7M96+PV - Rawdat Al Sidr - Al Ruwaiyat - Sharjah",
    "location_ar": "7M96+PV - ضاحية الرويضات - روضة السدر - الشارقة",
    "gallery": [
      "https://luxury-real-estate-media.b-cdn.net/al-rasikhoon/rawdat-al-sidr",
      "https://luxury-real-estate-media.b-cdn.net/al-rasikhoon/rawdat-al-sidr",
      "https://luxury-real-estate-media.b-cdn.net/al-rasikhoon/rawdat-al-sidr",
      "https://luxury-real-estate-media.b-cdn.net/al-rasikhoon/rawdat-al-sidr",
      "https://luxury-real-estate-media.b-cdn.net/al-rasikhoon/rawdat-al-sidr",
      "https://luxury-real-estate-media.b-cdn.net/al-rasikhoon/rawdat-al-sidr",
      "https://luxury-real-estate-media.b-cdn.net/al-rasikhoon/rawdat-al-sidr",
      "https://luxury-real-estate-media.b-cdn.net/al-rasikhoon/al-qasimia"
    ],
    "price_en": "Starting from AED 450,000",
    "area_en": "270-1080 sqm",
    "lat": null,
    "lng": null
  },
  {
    "slug": "al-qasimia-gate",
    "title_en": "Al Qasimia Gate Project - Sharjah",
    "title_ar": "مشروع بوابة القاسمية – إمارة الشارقة",
    "location_en": "24°58",
    "location_ar": "24°58",
    "gallery": [
      "https://luxury-real-estate-media.b-cdn.net/al-rasikhoon/al-qasimia",
      "https://luxury-real-estate-media.b-cdn.net/al-rasikhoon/al-qasimia",
      "https://luxury-real-estate-media.b-cdn.net/al-rasikhoon/al-qasimia",
      "https://luxury-real-estate-media.b-cdn.net/al-rasikhoon/al-qasimia",
      "https://luxury-real-estate-media.b-cdn.net/al-rasikhoon/al-qasimia",
      "https://luxury-real-estate-media.b-cdn.net/al-rasikhoon/rawdat-al-sidr-2",
      "https://luxury-real-estate-media.b-cdn.net/al-rasikhoon/rawdat-al-sidr-2",
      "https://luxury-real-estate-media.b-cdn.net/al-rasikhoon/rawdat-al-sidr-2",
      "https://luxury-real-estate-media.b-cdn.net/al-rasikhoon/rawdat-al-sidr-2",
      "https://luxury-real-estate-media.b-cdn.net/al-rasikhoon/rawdat-al-sidr-2"
    ],
    "price_en": "Competitive pricing",
    "area_en": "Various sizes available",
    "lat": null,
    "lng": null
  },
  {
    "slug": "rawdat-al-sidr-2",
    "title_en": "Rawdat Al Sidr 2",
    "title_ar": "روضة السدر 2",
    "location_en": "Rawdat Al Sidr - Sharjah",
    "location_ar": "روضة السدر - الشارقة",
    "gallery": [
      "https://luxury-real-estate-media.b-cdn.net/al-rasikhoon/rawdat-al-sidr-2",
      "https://luxury-real-estate-media.b-cdn.net/al-rasikhoon/rawdat-al-sidr-2",
      "https://luxury-real-estate-media.b-cdn.net/al-rasikhoon/rawdat-al-sidr-2",
      "https://luxury-real-estate-media.b-cdn.net/al-rasikhoon/rawdat-al-sidr-2",
      "https://luxury-real-estate-media.b-cdn.net/al-rasikhoon/rawdat-al-sidr-2",
      "https://luxury-real-estate-media.b-cdn.net/al-rasikhoon/rawdat-al-sidr-2",
      "https://luxury-real-estate-media.b-cdn.net/al-rasikhoon/rawdat-al-sidr-2",
      "https://luxury-real-estate-media.b-cdn.net/al-rasikhoon/al-saja-el-namoosajiya",
      "https://luxury-real-estate-media.b-cdn.net/al-rasikhoon/al-saja-el-namoosajiya",
      "https://luxury-real-estate-media.b-cdn.net/al-rasikhoon/al-saja-el-namoosajiya"
    ],
    "price_en": "All-inclusive price",
    "area_en": "270+ sqm",
    "lat": null,
    "lng": null
  },
  {
    "slug": "al-saja-el-namoosajiya",
    "title_en": "Sajaa 00 - Industrial Land Project",
    "title_ar": "الصجعة 00 - مشروع أراضٍ صناعية",
    "location_en": "Sajaa Industrial Area, near Emirates Industrial City and Emirates Road",
    "location_ar": "الصجعة الصناعية، بالقرب من مدينة الامارات الصناعية وشارع الامارات",
    "gallery": [
      "https://luxury-real-estate-media.b-cdn.net/al-rasikhoon/al-saja-el-namoosajiya",
      "https://luxury-real-estate-media.b-cdn.net/al-rasikhoon/al-saja-el-namoosajiya",
      "https://luxury-real-estate-media.b-cdn.net/al-rasikhoon/al-saja-el-namoosajiya"
    ],
    "price_en": "165 AED/sq.ft (all inclusive)",
    "area_en": "19,409-26,446 sqm",
    "lat": null,
    "lng": null
  }
]